tranpy/__init__.py
tranpy/data/__init__.py
tranpy/data/cache.py
tranpy/data/download.py
tranpy/data/datasets/NewEngland.pickle
tranpy/data/datasets/NineBusSystem.pickle
tranpy/data/datasets/registry.json
tranpy/data/models/registry.json
tranpy/datasets/__init__.py
tranpy/datasets/base.py
tranpy/datasets/loaders.py
tranpy/explainers/__init__.py
tranpy/explainers/base.py
tranpy/explainers/dalex.py
tranpy/explainers/lime.py
tranpy/explainers/shap.py
tranpy/models/__init__.py
tranpy/models/base.py
tranpy/models/classical.py
tranpy/models/ensemble.py
tranpy/models/neural.py
tranpy/models/pretrained.py
tranpy/simulation/__init__.py
tranpy/simulation/config.py
tranpy/simulation/dataset_generator.py
tranpy/simulation/events.py
tranpy/simulation/mock_engine.py
tranpy/simulation/model.py
tranpy/simulation/powerfactory_config.py
tranpy/simulation/results.py
tranpy/simulation/simulator.py
tranpy/utils/__init__.py
tranpy/utils/config.py
tranpy/utils/io.py
tranpy/utils/logging.py
tranpy_ai-0.1.4.dist-info/METADATA
tranpy_ai-0.1.4.dist-info/WHEEL
tranpy_ai-0.1.4.dist-info/top_level.txt
tranpy_ai-0.1.4.dist-info/RECORD
